Metadata-Version: 2.1
Name: AppiumGridServer
Version: 0.0.1b12
Summary: ChokChaisak
Home-page: https://test.pypi.org/user/ChokChaisak/
Author: ChokChaisak
Author-email: ChokChaisak@gmail.com
License: ChokChaisak
Keywords: AppiumGridServer
Platform: UNKNOWN
